py_xtdb/__init__.py
py_xtdb/xt.py
py_xtdb-0.5.1.dist-info/WHEEL
py_xtdb-0.5.1.dist-info/METADATA
py_xtdb-0.5.1.dist-info/RECORD
